tests/tools/vectors/waveform2.sv
module child3 (input logic a3);
endmodule

module child2(input logic a2);
child3 inst3(.a3(a2));
endmodule

module child1(input logic a1);
child2 inst2(.a2(a1));
endmodule

module top;
logic a;

child1 inst1(.a1(a));

initial begin
    $dumpfile("waveform2.vcd");
    $dumpvars(0, top);
    
    for (int i = 0; i < 10; i++) begin
        #10 a = i & 1;
    end
end

endmodule

tests/tools/vectors/waveform2.vcd
$date
    Feb  1, 2021  20:27:28
$end
$version
    TOOL:	xmsim(64)	19.03-s003
$end
$timescale
    1 ns
$end

$scope module top $end
$var reg       1 !    a $end

$scope module inst1 $end
$var wire      1 "    a1  $end

$scope module inst2 $end
$var wire      1 "    a2  $end

$scope module inst3 $end
$var wire      1 "    a3  $end
$upscope $end

$upscope $end

$upscope $end

$upscope $end

$enddefinitions $end
$dumpvars
x!
x"
$end
#10
0!
0"
#20
1!
1"
#30
0!
0"
#40
1!
1"
#50
0!
0"
#60
1!
1"
#70
0!
0"
#80
1!
1"
#90
0!
0"
#100
1!
1"
